README.rst
setup.py
whenis/__init__.py
whenis.egg-info/PKG-INFO
whenis.egg-info/SOURCES.txt
whenis.egg-info/dependency_links.txt
whenis.egg-info/entry_points.txt
whenis.egg-info/requires.txt
whenis.egg-info/top_level.txt