Metadata-Version: 1.1
Name: whenis
Version: 0.0.2
Summary: A command-line utility to convert timestamps between UTC and local timezones.
Home-page: https://github.com/tristaneuan/whenis
Author: Tristan Chong
Author-email: ong@tristaneuan.ch
License: MIT
Download-URL: https://github.com/tristaneuan/whenis/tarball/0.0.2
Keywords: time zone timezone conversion
Platform: UNKNOWN
